pypebbletimeline/__init__.py
pypebbletimeline/timeline.py
pypebbletimeline-0.1.1.dist-info/METADATA
pypebbletimeline-0.1.1.dist-info/WHEEL
pypebbletimeline-0.1.1.dist-info/top_level.txt
pypebbletimeline-0.1.1.dist-info/RECORD
